tokenspan/__init__.py
tokenspan/mergesort.py
tokenspan/span.py
tokenspan/tokentokens.py
tokenspan/tools.py
tokenspan-0.7.1.dist-info/LICENSE
tokenspan-0.7.1.dist-info/METADATA
tokenspan-0.7.1.dist-info/WHEEL
tokenspan-0.7.1.dist-info/top_level.txt
tokenspan-0.7.1.dist-info/RECORD
