Metadata-Version: 2.1
Name: tokenspan
Version: 0.7.1
Summary: Basic tools to tokenize (i.e. to construct atomic-entities/sub-strings of) a string, for Natural Language Processing (NLP). Usefull also for annotation, tree parsing, entity linking, ... (in fact, anything that links a string or its sub-parts to an other object). Key concepts are versatility to other librairies, and freedom to define many concepts on top of a string.
Home-page: https://framagit.org/nlp/tokenspan
Author: François Konschelle - IAM CHU Bordeaux France
Author-email: via.issue@only.please
License: GNU GENERAL PUBLIC LICENSE v.3
Platform: UNKNOWN
Classifier: Programming Language :: Python :: 3
Classifier: License :: OSI Approved :: GNU General Public License v3 (GPLv3)
Classifier: Operating System :: OS Independent
Classifier: Topic :: Scientific/Engineering :: Information Analysis
Classifier: Topic :: Text Processing
Classifier: Intended Audience :: Information Technology
Classifier: Intended Audience :: Science/Research
Requires-Python: >=3.6
License-File: LICENSE
